{"blog_vue_使用_tinymce_富文本编辑器.md":"BWNe544A","index.md":"CZAG1UuR","blog_taro_ci_持续集成框架的配置与使用.md":"DKXukDbu","blog_taro_小程序引入_painter_实现动态生成图片.md":"CKd_7jwy","blog_vitepress_使用_gitalk_添加评论功能.md":"B4wjbABt","blog_企微使用_weixin-js-sdk_分享_h5_页面到微信.md":"C4seN5Xe","blog_使用_githubpages_部署_vitepress.md":"WV9R-a3T","blog_如何搭建_electron_项目.md":"oAyxnTqG","blog_如何搭建_vitepress.md":"D2hj1N1M","blog_尝试用_vue_写一个表格组件.md":"D83PSrRE","blog_vue_引入_wps_js_sdk.md":"BZ7u564j","blog_node_环境使用_puppeteer_实现调用wps_js_sdk.md":"BTTRtbQO","essay_关于_gitee_的仓库镜像管理功能.md":"xa6sZIRJ","essay_如何快速完成_microsoft_rewards_积分任务.md":"BxSi_g1G","chat_书架.md":"CksjjNIf","blog_vitepress_预览组件.md":"Cjn9Edvv","blog_gitalk_自动初始化评论.md":"BUp2s0O-","template.md":"PLkk8pNx","blog_企微使用_wecom_jssdk_分享消息卡片到会话.md":"BhJsRnsF","note_黑板.md":"BCqE5Djk","note_handbook_lodash.md":"3fTn82kj","note_handbook_git.md":"VlX2RRDl","note_handbook_vs_code.md":"Bvm2waN8","note_handbook_site.md":"CUCeTxzO","note_handbook_pm2.md":"DPMS-otZ","note_handbook_nvm.md":"D3wR2hyA"}
